fermo_core/__init__.py
fermo_core/main.py
fermo_core/config/__init__.py
fermo_core/config/class_default_settings.py
fermo_core/config/schema.json
fermo_core/data_analysis/__init__.py
fermo_core/data_analysis/class_analysis_manager.py
fermo_core/data_analysis/annotation_manager/__init__.py
fermo_core/data_analysis/annotation_manager/class_adduct_annotator.py
fermo_core/data_analysis/annotation_manager/class_annotation_manager.py
fermo_core/data_analysis/annotation_manager/class_fragment_annotator.py
fermo_core/data_analysis/annotation_manager/class_mod_cos_annotator.py
fermo_core/data_analysis/annotation_manager/class_ms2deepscore_annotator.py
fermo_core/data_analysis/annotation_manager/class_ms2query_annotator.py
fermo_core/data_analysis/annotation_manager/class_mzmine_ann_parser.py
fermo_core/data_analysis/annotation_manager/class_neutral_loss_annotator.py
fermo_core/data_analysis/blank_assigner/__init__.py
fermo_core/data_analysis/blank_assigner/class_blank_assigner.py
fermo_core/data_analysis/chrom_trace_calculator/__init__.py
fermo_core/data_analysis/chrom_trace_calculator/class_chrom_trace_calculator.py
fermo_core/data_analysis/feature_filter/__init__.py
fermo_core/data_analysis/feature_filter/class_feature_filter.py
fermo_core/data_analysis/group_assigner/__init__.py
fermo_core/data_analysis/group_assigner/class_group_assigner.py
fermo_core/data_analysis/group_factor_assigner/__init__.py
fermo_core/data_analysis/group_factor_assigner/class_group_factor_assigner.py
fermo_core/data_analysis/phenotype_manager/__init__.py
fermo_core/data_analysis/phenotype_manager/class_phen_qual_assigner.py
fermo_core/data_analysis/phenotype_manager/class_phen_quant_ass.py
fermo_core/data_analysis/phenotype_manager/class_phenotype_manager.py
fermo_core/data_analysis/score_assigner/__init__.py
fermo_core/data_analysis/score_assigner/class_score_assigner.py
fermo_core/data_analysis/sim_networks_manager/__init__.py
fermo_core-0.7.0.dist-info/METADATA
fermo_core-0.7.0.dist-info/WHEEL
fermo_core-0.7.0.dist-info/entry_points.txt
fermo_core-0.7.0.dist-info/licenses/LICENSE
fermo_core-0.7.0.dist-info/RECORD
