Metadata-Version: 2.4
Name: fermo_core
Version: 0.7.0
Summary: Data processing/analysis functionality of metabolomics dashboard FERMO
Project-URL: Website, https://fermo.bioinformatics.nl/
Project-URL: Repository, https://github.com/fermo-metabolomics/fermo_core
Project-URL: Documentation, https://fermo-metabolomics.github.io/fermo_docs/
Author-email: "Mitja M. Zdouc" <zdoucmm@gmail.com>
License-File: LICENSE
Keywords: cheminformatics,genomics,metabolomics
Classifier: Development Status :: 4 - Beta
Classifier: License :: OSI Approved :: MIT License
Classifier: Operating System :: POSIX :: Linux
Classifier: Programming Language :: Python :: 3.11
Classifier: Topic :: Scientific/Engineering :: Bio-Informatics
Classifier: Topic :: Scientific/Engineering :: Chemistry
Requires-Python: <3.12,>=3.11
Requires-Dist: argparse==1.4.0
Requires-Dist: coloredlogs==15.0.1
Requires-Dist: jsonschema==4.19.0
Requires-Dist: keras==2.15.0
Requires-Dist: matchms==0.24.0
Requires-Dist: ms2deepscore==0.5.0
Requires-Dist: pandas==2.0.3
Requires-Dist: pydantic==2.5.2
Requires-Dist: pyteomics==4.6.3
Requires-Dist: statsmodels==0.14.4
Provides-Extra: dev
Requires-Dist: pre-commit~=3.4.0; extra == 'dev'
Requires-Dist: pytest-cov~=4.1.0; extra == 'dev'
Requires-Dist: pytest~=7.4.2; extra == 'dev'
Requires-Dist: ruff~=0.4.4; extra == 'dev'
Provides-Extra: doc
Requires-Dist: sphinx-autoapi~=3.6; extra == 'doc'
Requires-Dist: sphinx-rtd-theme~=3.0; extra == 'doc'
Requires-Dist: sphinx~=8.2; extra == 'doc'
